cloud/__init__.py
cloud/__main__.py
cloud/application/cli.py
gdcloudlib-0.0.1.dist-info/entry_points.txt
gdcloudlib-0.0.1.dist-info/WHEEL
gdcloudlib-0.0.1.dist-info/METADATA
gdcloudlib-0.0.1.dist-info/RECORD
